pyaudiodevice/__init__.py
pyaudiodevice/audio_common.py
pyaudiodevice/audio_device_cmdlets.py
pyaudiodevice/default_communication_playback.py
pyaudiodevice/default_communication_recording.py
pyaudiodevice/default_playback.py
pyaudiodevice/lib/AudioDeviceCmdlets.dll
pyaudiodevice-1.0.8.dist-info/METADATA
pyaudiodevice-1.0.8.dist-info/WHEEL
pyaudiodevice-1.0.8.dist-info/top_level.txt
pyaudiodevice-1.0.8.dist-info/RECORD
