Metadata-Version: 2.4
Name: pyaudiodevice
Version: 1.0.8
Summary: python version developed based on AudioDeviceCmdlets.
Home-page: https://github.com/letmeNo1/PyAudioDeviceCmdlets
Author: hank.huang
Author-email: hank.huang550@gmail.com
Classifier: Programming Language :: Python :: 3
Classifier: License :: OSI Approved :: MIT License
Classifier: Operating System :: OS Independent
Requires-Python: >=3.6
Dynamic: author
Dynamic: author-email
Dynamic: classifier
Dynamic: description
Dynamic: description-content-type
Dynamic: home-page
Dynamic: requires-python
Dynamic: summary
